Lab3-FSM/task4/lfsr_7.sv
module lfsr_7 (
    input   logic       clk,
    input   logic       rst,
    input   logic       en,
    output  logic [6:0] data_out
);

logic [6:0] sreg;

always_ff @(posedge clk or posedge rst)
    if (rst)
        sreg <= 7'b1;
    else if (en)
        sreg <= {sreg[5:0], sreg[2] ^ sreg[6]};

assign data_out = sreg;
endmodule

Lab3-FSM/task4/delay.sv
module delay #(
    parameter WIDTH = 10    // no of bits in delay counter
)(
    input   logic               clk,        // clock signal
    input   logic               rst,        // reset signal
    input   logic               trigger,    // trigger input signal
    output  logic               time_out    // output pulse signal
);
    // Declare counter
    logic [WIDTH-1:0]   count = {WIDTH{1'b0}};

    // Define our states
    typedef enum {IDLE, COUNTING, TIME_OUT, WAIT_LOW}  my_state;
    my_state current_state, next_state;
    logic [6:0] randnum;

    // counter
    always_ff @(posedge clk or posedge rst)
        if (rst | trigger | count=={WIDTH{1'b0}}) count <= randnum - 1;
        else                                count <= count - 1'b1;

    // state transition
    always_ff @(posedge clk or posedge rst)
        if (rst)    current_state <= IDLE;
        else        current_state <= next_state; 

    // next state logic
    always_comb
        case (current_state)
            IDLE:       if (trigger==1'b1)  next_state = COUNTING;
                        else    next_state = current_state;
            COUNTING:   if (count=={WIDTH{1'b0}}) next_state = TIME_OUT;
                        else    next_state = current_state;
            TIME_OUT:   if (trigger==1'b1)  next_state = WAIT_LOW;
                        else    next_state = IDLE;
            WAIT_LOW:   if (trigger==1'b0)  next_state = IDLE;
                        else    next_state = current_state;
            default: next_state = IDLE;
        endcase
    
    // output logic
    always_comb
        case (current_state)
            IDLE:       time_out = 1'b0;
            COUNTING:   time_out = 1'b0;
            TIME_OUT:   time_out = 1'b1;
            WAIT_LOW:   time_out = 1'b0;
            default:    time_out = 1'b0;
        endcase

    lfsr_7 randgen(
        .clk(clk),
        .rst(rst),
        .en(1),
        .data_out(randnum)
    );

endmodule

Lab3-FSM/task4/clktick.sv
module clktick #(
    parameter WIDTH = 16
)(
  // interface signals
  input  logic             clk,      // clock 
  input  logic             rst,      // reset
  input  logic             en,       // enable signal
  input  logic [WIDTH-1:0] N,     	 // clock divided by N+1
  output logic  		   tick      // tick output
);

logic [WIDTH-1:0] count;

always_ff @ (posedge clk or posedge rst)
    if (rst) begin
        tick <= 1'b0;
        count <= N;  
        end
    else if (en) begin
        if (count == 0) begin
            tick <= 1'b1;
            count <= N;
            end
        else begin
            tick <= 1'b0;
            count <= count - 1'b1;
            end
        end
endmodule

Lab3-FSM/task4/f1_fsm.sv
module f1_fsm (
    input   logic       rst,
    input   logic       en,
    input   logic       clk,
    output  logic [7:0] data_out
);

    typedef enum { S0, S1, S2, S3, S4, S5, S6, S7, S8, S9 } f1_states;
    f1_states state, next_state;
    logic cmd_seq, cmd_delay, clkEn, delayEn;

    always_ff @(posedge clk or posedge rst) begin
        cmd_delay <= 0;
        cmd_seq <= 0;
        if (rst)
            state <= S0;
        else if (en) begin
            if (state == S8) begin
                cmd_delay <= 1;
                state <= next_state;
        end
            if (state == S9) begin
                if (delayEn)
                    state <= next_state;
            end
            else begin 
                cmd_seq <= 1;
                if (clkEn)
                    state <= next_state;
            end
        end
    end

    always_comb 
        case (state)
            S0 : data_out = 8'b00000000; 
            S1 : data_out = 8'b00000001;
            S2 : data_out = 8'b00000011;
            S3 : data_out = 8'b00000111;
            S4 : data_out = 8'b00001111;
            S5 : data_out = 8'b00011111;
            S6 : data_out = 8'b00111111;
            S7 : data_out = 8'b01111111;
            S8 : data_out = 8'b11111111;
            S9 : data_out = 8'b11111111;
            default : data_out = 8'b00000000;
        endcase


    always_comb begin
        case (state)
            S0 : next_state = S1;
            S1 : next_state = S2;
            S2 : next_state = S3;
            S3 : next_state = S4;
            S4 : next_state = S5;
            S5 : next_state = S6;
            S6 : next_state = S7;
            S7 : next_state = S8;
            S8 : next_state = S9;
            S9 : next_state = S0;
            default : next_state = S0;
        endcase
    end

clktick clocktick (
    .clk(clk),
    .rst(rst),
    .N(47),
    .en(cmd_seq),
    .tick(clkEn)
);

delay randdelay (
    .clk(clk),
    .rst(rst),
    .trigger(cmd_delay),
    .time_out(delayEn)
);

endmodule

Lab3-FSM/task4/f1_fsm.vcd
$version Generated by VerilatedVcd $end
$date Sat Nov  2 02:25:54 2024 $end
$timescale 1ps $end

 $scope module TOP $end
  $var wire  1 0 clk $end
  $var wire  8 1 data_out [7:0] $end
  $var wire  1 / en $end
  $var wire  1 . rst $end
  $scope module f1_fsm $end
   $var wire  1 0 clk $end
   $var wire  1 ' clkEn $end
   $var wire  1 & cmd_delay $end
   $var wire  1 % cmd_seq $end
   $var wire  8 1 data_out [7:0] $end
   $var wire  1 ( delayEn $end
   $var wire  1 / en $end
   $var wire 32 $ next_state [31:0] $end
   $var wire  1 . rst $end
   $var wire 32 # state [31:0] $end
   $scope module clocktick $end
    $var wire 16 3 N [15:0] $end
    $var wire 32 2 WIDTH [31:0] $end
    $var wire  1 0 clk $end
    $var wire 16 ) count [15:0] $end
    $var wire  1 % en $end
    $var wire  1 . rst $end
    $var wire  1 ' tick $end
   $upscope $end
   $scope module randdelay $end
    $var wire 32 4 WIDTH [31:0] $end
    $var wire  1 0 clk $end
    $var wire 10 * count [9:0] $end
    $var wire 32 + current_state [31:0] $end
    $var wire 32 , next_state [31:0] $end
    $var wire  7 - randnum [6:0] $end
    $var wire  1 . rst $end
    $var wire  1 ( time_out $end
    $var wire  1 & trigger $end
    $scope module randgen $end
     $var wire  1 0 clk $end
     $var wire  7 - data_out [6:0] $end
     $var wire  1 5 en $end
     $var wire  1 . rst $end
     $var wire  7 - sreg [6:0] $end
    $upscope $end
   $upscope $end
  $upscope $end
 $upscope $end
$enddefinitions $end


#0
b00000000000000000000000000000000 #
b00000000000000000000000000000000 $
0%
0&
0'
0(
b0000000000000000 )
b0000000000 *
b00000000000000000000000000000000 +
b00000000000000000000000000000000 ,
b0000000 -
0.
0/
10
b00000000 1
b00000000000000000000000000010000 2
b0000000000101111 3
b00000000000000000000000000001010 4
15
#1
b00000000000000000000000000000001 $
00
#2
b1111111111 *
1.
10
#3
b0000000000101111 )
b0000001 -
00
#4
b0000000000 *
10
#5
00
#6
0.
10
#7
00
#8
b0000010 -
1/
10
#9
00
#10
1%
b0000000001 *
b0000100 -
10
#11
00
#12
b0000000000101110 )
b0000000000 *
b0001001 -
10
#13
00
#14
b0000000000101101 )
b0000001000 *
b0010010 -
10
#15
00
#16
b0000000000101100 )
b0000000111 *
b0100100 -
10
#17
00
#18
b0000000000101011 )
b0000000110 *
b1001001 -
10
#19
00
#20
b0000000000101010 )
b0000000101 *
b0010011 -
10
#21
00
#22
b0000000000101001 )
b0000000100 *
b0100110 -
10
#23
00
#24
b0000000000101000 )
b0000000011 *
b1001101 -
10
#25
00
#26
b0000000000100111 )
b0000000010 *
b0011010 -
10
#27
00
#28
b0000000000100110 )
b0000000001 *
b0110100 -
10
#29
00
#30
b0000000000100101 )
b0000000000 *
b1101001 -
10
#31
00
#32
b0000000000100100 )
b0001101000 *
b1010011 -
10
#33
00
#34
b0000000000100011 )
b0001100111 *
b0100111 -
10
#35
00
#36
b0000000000100010 )
b0001100110 *
b1001111 -
10
#37
00
#38
b0000000000100001 )
b0001100101 *
b0011110 -
10
#39
00
#40
b0000000000100000 )
b0001100100 *
b0111101 -
10
#41
00
#42
b0000000000011111 )
b0001100011 *
b1111011 -
10
#43
00
#44
b0000000000011110 )
b0001100010 *
b1110111 -
10
#45
00
#46
b0000000000011101 )
b0001100001 *
b1101110 -
10
#47
00
#48
b0000000000011100 )
b0001100000 *
b1011100 -
10
#49
00
#50
b0000000000011011 )
b0001011111 *
b0111000 -
10
#51
00
#52
b0000000000011010 )
b0001011110 *
b1110000 -
10
#53
00
#54
b0000000000011001 )
b0001011101 *
b1100001 -
10
#55
00
#56
b0000000000011000 )
b0001011100 *
b1000011 -
10
#57
00
#58
b0000000000010111 )
b0001011011 *
b0000111 -
10
#59
00
#60
b0000000000010110 )
b0001011010 *
b0001111 -
10
#61
00
#62
b0000000000010101 )
b0001011001 *
b0011111 -
10
#63
00
#64
b0000000000010100 )
b0001011000 *
b0111111 -
10
#65
00
#66
b0000000000010011 )
b0001010111 *
b1111111 -
10
#67
00
#68
b0000000000010010 )
b0001010110 *
b1111110 -
10
#69
00
#70
b0000000000010001 )
b0001010101 *
b1111100 -
10
#71
00
#72
b0000000000010000 )
b0001010100 *
b1111000 -
10
#73
00
#74
b0000000000001111 )
b0001010011 *
b1110001 -
10
#75
00
#76
b0000000000001110 )
b0001010010 *
b1100011 -
10
#77
00
#78
b0000000000001101 )
b0001010001 *
b1000111 -
10
#79
00
#80
b0000000000001100 )
b0001010000 *
b0001110 -
10
#81
00
#82
b0000000000001011 )
b0001001111 *
b0011101 -
10
#83
00
#84
b0000000000001010 )
b0001001110 *
b0111011 -
10
#85
00
#86
b0000000000001001 )
b0001001101 *
b1110110 -
10
#87
00
#88
b0000000000001000 )
b0001001100 *
b1101100 -
10
#89
00
#90
b0000000000000111 )
b0001001011 *
b1011000 -
10
#91
00
#92
b0000000000000110 )
b0001001010 *
b0110001 -
10
#93
00
#94
b0000000000000101 )
b0001001001 *
b1100010 -
10
#95
00
#96
b0000000000000100 )
b0001001000 *
b1000101 -
10
#97
00
#98
b0000000000000011 )
b0001000111 *
b0001010 -
10
#99
00
#100
b0000000000000010 )
b0001000110 *
b0010100 -
10
#101
00
#102
b0000000000000001 )
b0001000101 *
b0101001 -
10
#103
00
#104
b0000000000000000 )
b0001000100 *
b1010010 -
10
#105
00
#106
1'
b0000000000101111 )
b0001000011 *
b0100101 -
10
#107
00
#108
b00000000000000000000000000000001 #
b00000000000000000000000000000010 $
0'
b0000000000101110 )
b0001000010 *
b1001011 -
10
b00000001 1
#109
00
#110
b0000000000101101 )
b0001000001 *
b0010111 -
10
#111
00
#112
b0000000000101100 )
b0001000000 *
b0101111 -
10
#113
00
#114
b0000000000101011 )
b0000111111 *
b1011111 -
10
#115
00
#116
b0000000000101010 )
b0000111110 *
b0111110 -
10
#117
00
#118
b0000000000101001 )
b0000111101 *
b1111101 -
10
#119
00
#120
b0000000000101000 )
b0000111100 *
b1111010 -
10
#121
00
#122
b0000000000100111 )
b0000111011 *
b1110101 -
10
#123
00
#124
b0000000000100110 )
b0000111010 *
b1101010 -
10
#125
00
#126
b0000000000100101 )
b0000111001 *
b1010101 -
10
#127
00
#128
b0000000000100100 )
b0000111000 *
b0101010 -
10
#129
00
#130
b0000000000100011 )
b0000110111 *
b1010100 -
10
#131
00
#132
b0000000000100010 )
b0000110110 *
b0101000 -
10
#133
00
#134
b0000000000100001 )
b0000110101 *
b1010000 -
10
#135
00
#136
b0000000000100000 )
b0000110100 *
b0100001 -
10
#137
00
#138
b0000000000011111 )
b0000110011 *
b1000010 -
10
#139
00
#140
b0000000000011110 )
b0000110010 *
b0000101 -
10
#141
00
#142
b0000000000011101 )
b0000110001 *
b0001011 -
10
#143
00
#144
b0000000000011100 )
b0000110000 *
b0010110 -
10
#145
00
#146
b0000000000011011 )
b0000101111 *
b0101101 -
10
#147
00
#148
b0000000000011010 )
b0000101110 *
b1011011 -
10
#149
00
#150
b0000000000011001 )
b0000101101 *
b0110111 -
10
#151
00
#152
b0000000000011000 )
b0000101100 *
b1101111 -
10
#153
00
#154
b0000000000010111 )
b0000101011 *
b1011110 -
10
#155
00
#156
b0000000000010110 )
b0000101010 *
b0111100 -
10
#157
00
#158
b0000000000010101 )
b0000101001 *
b1111001 -
10
#159
00
#160
b0000000000010100 )
b0000101000 *
b1110011 -
10
#161
00
#162
b0000000000010011 )
b0000100111 *
b1100111 -
10
#163
00
#164
b0000000000010010 )
b0000100110 *
b1001110 -
10
#165
00
#166
b0000000000010001 )
b0000100101 *
b0011100 -
10
#167
00
#168
b0000000000010000 )
b0000100100 *
b0111001 -
10
#169
00
#170
b0000000000001111 )
b0000100011 *
b1110010 -
10
#171
00
#172
b0000000000001110 )
b0000100010 *
b1100101 -
10
#173
00
#174
b0000000000001101 )
b0000100001 *
b1001010 -
10
#175
00
#176
b0000000000001100 )
b0000100000 *
b0010101 -
10
#177
00
#178
b0000000000001011 )
b0000011111 *
b0101011 -
10
#179
00
#180
b0000000000001010 )
b0000011110 *
b1010110 -
10
#181
00
#182
b0000000000001001 )
b0000011101 *
b0101100 -
10
#183
00
#184
b0000000000001000 )
b0000011100 *
b1011001 -
10
#185
00
#186
b0000000000000111 )
b0000011011 *
b0110011 -
10
#187
00
#188
b0000000000000110 )
b0000011010 *
b1100110 -
10
#189
00
#190
b0000000000000101 )
b0000011001 *
b1001100 -
10
#191
00
#192
b0000000000000100 )
b0000011000 *
b0011000 -
10
#193
00
#194
b0000000000000011 )
b0000010111 *
b0110000 -
10
#195
00
#196
b0000000000000010 )
b0000010110 *
b1100000 -
10
#197
00
#198
b0000000000000001 )
b0000010101 *
b1000001 -
10
#199
00
#200
b0000000000000000 )
b0000010100 *
b0000011 -
10
#201
00
#202
1'
b0000000000101111 )
b0000010011 *
b0000110 -
10
#203
00
#204
b00000000000000000000000000000010 #
b00000000000000000000000000000011 $
0'
b0000000000101110 )
b0000010010 *
b0001101 -
10
b00000011 1
#205
00
#206
b0000000000101101 )
b0000010001 *
b0011011 -
10
#207
00
#208
b0000000000101100 )
b0000010000 *
b0110110 -
10
#209
00
#210
b0000000000101011 )
b0000001111 *
b1101101 -
10
#211
00
#212
b0000000000101010 )
b0000001110 *
b1011010 -
10
#213
00
#214
b0000000000101001 )
b0000001101 *
b0110101 -
10
#215
00
#216
b0000000000101000 )
b0000001100 *
b1101011 -
10
#217
00
#218
b0000000000100111 )
b0000001011 *
b1010111 -
10
#219
00
#220
b0000000000100110 )
b0000001010 *
b0101110 -
10
#221
00
#222
b0000000000100101 )
b0000001001 *
b1011101 -
10
#223
00
#224
b0000000000100100 )
b0000001000 *
b0111010 -
10
#225
00
#226
b0000000000100011 )
b0000000111 *
b1110100 -
10
#227
00
#228
b0000000000100010 )
b0000000110 *
b1101000 -
10
#229
00
#230
b0000000000100001 )
b0000000101 *
b1010001 -
10
#231
00
#232
b0000000000100000 )
b0000000100 *
b0100011 -
10
#233
00
#234
b0000000000011111 )
b0000000011 *
b1000110 -
10
#235
00
#236
b0000000000011110 )
b0000000010 *
b0001100 -
10
#237
00
#238
b0000000000011101 )
b0000000001 *
b0011001 -
10
#239
00
#240
b0000000000011100 )
b0000000000 *
b0110010 -
10
#241
00
#242
b0000000000011011 )
b0000110001 *
b1100100 -
10
#243
00
#244
b0000000000011010 )
b0000110000 *
b1001000 -
10
#245
00
#246
b0000000000011001 )
b0000101111 *
b0010001 -
10
#247
00
#248
b0000000000011000 )
b0000101110 *
b0100010 -
10
#249
00
#250
b0000000000010111 )
b0000101101 *
b1000100 -
10
#251
00
#252
b0000000000010110 )
b0000101100 *
b0001000 -
10
#253
00
#254
b0000000000010101 )
b0000101011 *
b0010000 -
10
#255
00
#256
b0000000000010100 )
b0000101010 *
b0100000 -
10
#257
00
#258
b0000000000010011 )
b0000101001 *
b1000000 -
10
#259
00
#260
b0000000000010010 )
b0000101000 *
b0000001 -
10
#261
00
#262
b0000000000010001 )
b0000100111 *
b0000010 -
10
#263
00
#264
b0000000000010000 )
b0000100110 *
b0000100 -
10
#265
00
#266
b0000000000001111 )
b0000100101 *
b0001001 -
10
#267
00
#268
b0000000000001110 )
b0000100100 *
b0010010 -
10
#269
00
#270
b0000000000001101 )
b0000100011 *
b0100100 -
10
#271
00
#272
b0000000000001100 )
b0000100010 *
b1001001 -
10
#273
00
#274
b0000000000001011 )
b0000100001 *
b0010011 -
10
#275
00
#276
b0000000000001010 )
b0000100000 *
b0100110 -
10
#277
00
#278
b0000000000001001 )
b0000011111 *
b1001101 -
10
#279
00
#280
b0000000000001000 )
b0000011110 *
b0011010 -
10
#281
00
#282
b0000000000000111 )
b0000011101 *
b0110100 -
10
#283
00
#284
b0000000000000110 )
b0000011100 *
b1101001 -
10
#285
00
#286
b0000000000000101 )
b0000011011 *
b1010011 -
10
#287
00
#288
b0000000000000100 )
b0000011010 *
b0100111 -
10
#289
00
#290
b0000000000000011 )
b0000011001 *
b1001111 -
10
#291
00
#292
b0000000000000010 )
b0000011000 *
b0011110 -
10
#293
00
#294
b0000000000000001 )
b0000010111 *
b0111101 -
10
#295
00
#296
b0000000000000000 )
b0000010110 *
b1111011 -
10
#297
00
#298
1'
b0000000000101111 )
b0000010101 *
b1110111 -
10
#299
00
#300
b00000000000000000000000000000011 #
b00000000000000000000000000000100 $
0'
b0000000000101110 )
b0000010100 *
b1101110 -
10
b00000111 1
#301
00
#302
b0000000000101101 )
b0000010011 *
b1011100 -
10
#303
00
#304
b0000000000101100 )
b0000010010 *
b0111000 -
10
#305
00
#306
b0000000000101011 )
b0000010001 *
b1110000 -
10
#307
00
#308
b0000000000101010 )
b0000010000 *
b1100001 -
10
#309
00
#310
b0000000000101001 )
b0000001111 *
b1000011 -
10
#311
00
#312
b0000000000101000 )
b0000001110 *
b0000111 -
10
#313
00
#314
b0000000000100111 )
b0000001101 *
b0001111 -
10
#315
00
#316
b0000000000100110 )
b0000001100 *
b0011111 -
10
#317
00
#318
b0000000000100101 )
b0000001011 *
b0111111 -
10
#319
00
#320
b0000000000100100 )
b0000001010 *
b1111111 -
10
#321
00
#322
b0000000000100011 )
b0000001001 *
b1111110 -
10
#323
00
#324
b0000000000100010 )
b0000001000 *
b1111100 -
10
#325
00
#326
b0000000000100001 )
b0000000111 *
b1111000 -
10
#327
00
#328
b0000000000100000 )
b0000000110 *
b1110001 -
10
#329
00
#330
b0000000000011111 )
b0000000101 *
b1100011 -
10
#331
00
#332
b0000000000011110 )
b0000000100 *
b1000111 -
10
#333
00
#334
b0000000000011101 )
b0000000011 *
b0001110 -
10
#335
00
#336
b0000000000011100 )
b0000000010 *
b0011101 -
10
#337
00
#338
b0000000000011011 )
b0000000001 *
b0111011 -
10
#339
00
#340
b0000000000011010 )
b0000000000 *
b1110110 -
10
#341
00
#342
b0000000000011001 )
b0001110101 *
b1101100 -
10
#343
00
#344
b0000000000011000 )
b0001110100 *
b1011000 -
10
#345
00
#346
b0000000000010111 )
b0001110011 *
b0110001 -
10
#347
00
#348
b0000000000010110 )
b0001110010 *
b1100010 -
10
#349
00
#350
b0000000000010101 )
b0001110001 *
b1000101 -
10
#351
00
#352
b0000000000010100 )
b0001110000 *
b0001010 -
10
#353
00
#354
b0000000000010011 )
b0001101111 *
b0010100 -
10
#355
00
#356
b0000000000010010 )
b0001101110 *
b0101001 -
10
#357
00
#358
b0000000000010001 )
b0001101101 *
b1010010 -
10
#359
00
#360
b0000000000010000 )
b0001101100 *
b0100101 -
10
#361
00
#362
b0000000000001111 )
b0001101011 *
b1001011 -
10
#363
00
#364
b0000000000001110 )
b0001101010 *
b0010111 -
10
#365
00
#366
b0000000000001101 )
b0001101001 *
b0101111 -
10
#367
00
#368
b0000000000001100 )
b0001101000 *
b1011111 -
10
#369
00
#370
b0000000000001011 )
b0001100111 *
b0111110 -
10
#371
00
#372
b0000000000001010 )
b0001100110 *
b1111101 -
10
#373
00
#374
b0000000000001001 )
b0001100101 *
b1111010 -
10
#375
00
#376
b0000000000001000 )
b0001100100 *
b1110101 -
10
#377
00
#378
b0000000000000111 )
b0001100011 *
b1101010 -
10
#379
00
#380
b0000000000000110 )
b0001100010 *
b1010101 -
10
#381
00
#382
b0000000000000101 )
b0001100001 *
b0101010 -
10
#383
00
#384
b0000000000000100 )
b0001100000 *
b1010100 -
10
#385
00
#386
b0000000000000011 )
b0001011111 *
b0101000 -
10
#387
00
#388
b0000000000000010 )
b0001011110 *
b1010000 -
10
#389
00
#390
b0000000000000001 )
b0001011101 *
b0100001 -
10
#391
00
#392
b0000000000000000 )
b0001011100 *
b1000010 -
10
#393
00
#394
1'
b0000000000101111 )
b0001011011 *
b0000101 -
10
#395
00
#396
b00000000000000000000000000000100 #
b00000000000000000000000000000101 $
0'
b0000000000101110 )
b0001011010 *
b0001011 -
10
b00001111 1
#397
00
#398
b0000000000101101 )
b0001011001 *
b0010110 -
10
#399
00
#400
b0000000000101100 )
b0001011000 *
b0101101 -
10
#401
00
#402
b0000000000101011 )
b0001010111 *
b1011011 -
10
#403
00
#404
b0000000000101010 )
b0001010110 *
b0110111 -
10
#405
00
#406
b0000000000101001 )
b0001010101 *
b1101111 -
10
#407
00
#408
b0000000000101000 )
b0001010100 *
b1011110 -
10
#409
00
#410
b0000000000100111 )
b0001010011 *
b0111100 -
10
#411
00
#412
b0000000000100110 )
b0001010010 *
b1111001 -
10
#413
00
#414
b0000000000100101 )
b0001010001 *
b1110011 -
10
#415
00
#416
b0000000000100100 )
b0001010000 *
b1100111 -
10
#417
00
#418
b0000000000100011 )
b0001001111 *
b1001110 -
10
#419
00
#420
b0000000000100010 )
b0001001110 *
b0011100 -
10
#421
00
#422
b0000000000100001 )
b0001001101 *
b0111001 -
10
#423
00
#424
b0000000000100000 )
b0001001100 *
b1110010 -
10
#425
00
#426
b0000000000011111 )
b0001001011 *
b1100101 -
10
#427
00
#428
b0000000000011110 )
b0001001010 *
b1001010 -
10
#429
00
#430
b0000000000011101 )
b0001001001 *
b0010101 -
10
#431
00
#432
b0000000000011100 )
b0001001000 *
b0101011 -
10
#433
00
#434
b0000000000011011 )
b0001000111 *
b1010110 -
10
#435
00
#436
b0000000000011010 )
b0001000110 *
b0101100 -
10
#437
00
#438
b0000000000011001 )
b0001000101 *
b1011001 -
10
#439
00
#440
b0000000000011000 )
b0001000100 *
b0110011 -
10
#441
00
#442
b0000000000010111 )
b0001000011 *
b1100110 -
10
#443
00
#444
b0000000000010110 )
b0001000010 *
b1001100 -
10
#445
00
#446
b0000000000010101 )
b0001000001 *
b0011000 -
10
#447
00
#448
b0000000000010100 )
b0001000000 *
b0110000 -
10
#449
00
#450
b0000000000010011 )
b0000111111 *
b1100000 -
10
#451
00
#452
b0000000000010010 )
b0000111110 *
b1000001 -
10
#453
00
#454
b0000000000010001 )
b0000111101 *
b0000011 -
10
#455
00
#456
b0000000000010000 )
b0000111100 *
b0000110 -
10
#457
00
#458
b0000000000001111 )
b0000111011 *
b0001101 -
10
#459
00
#460
b0000000000001110 )
b0000111010 *
b0011011 -
10
#461
00
#462
b0000000000001101 )
b0000111001 *
b0110110 -
10
#463
00
#464
b0000000000001100 )
b0000111000 *
b1101101 -
10
#465
00
#466
b0000000000001011 )
b0000110111 *
b1011010 -
10
#467
00
#468
b0000000000001010 )
b0000110110 *
b0110101 -
10
#469
00
#470
b0000000000001001 )
b0000110101 *
b1101011 -
10
#471
00
#472
b0000000000001000 )
b0000110100 *
b1010111 -
10
#473
00
#474
b0000000000000111 )
b0000110011 *
b0101110 -
10
#475
00
#476
b0000000000000110 )
b0000110010 *
b1011101 -
10
#477
00
#478
b0000000000000101 )
b0000110001 *
b0111010 -
10
#479
00
#480
b0000000000000100 )
b0000110000 *
b1110100 -
10
#481
00
#482
b0000000000000011 )
b0000101111 *
b1101000 -
10
#483
00
#484
b0000000000000010 )
b0000101110 *
b1010001 -
10
#485
00
#486
b0000000000000001 )
b0000101101 *
b0100011 -
10
#487
00
#488
b0000000000000000 )
b0000101100 *
b1000110 -
10
#489
00
#490
1'
b0000000000101111 )
b0000101011 *
b0001100 -
10
#491
00
#492
b00000000000000000000000000000101 #
b00000000000000000000000000000110 $
0'
b0000000000101110 )
b0000101010 *
b0011001 -
10
b00011111 1
#493
00
#494
b0000000000101101 )
b0000101001 *
b0110010 -
10
#495
00
#496
b0000000000101100 )
b0000101000 *
b1100100 -
10
#497
00
#498
b0000000000101011 )
b0000100111 *
b1001000 -
10
#499
00
#500
b0000000000101010 )
b0000100110 *
b0010001 -
10
#501
00
#502
b0000000000101001 )
b0000100101 *
b0100010 -
10
#503
00
#504
b0000000000101000 )
b0000100100 *
b1000100 -
10
#505
00
#506
b0000000000100111 )
b0000100011 *
b0001000 -
10
#507
00
#508
b0000000000100110 )
b0000100010 *
b0010000 -
10
#509
00
#510
b0000000000100101 )
b0000100001 *
b0100000 -
10
#511
00
#512
b0000000000100100 )
b0000100000 *
b1000000 -
10
#513
00
#514
b0000000000100011 )
b0000011111 *
b0000001 -
10
#515
00
#516
b0000000000100010 )
b0000011110 *
b0000010 -
10
#517
00
#518
b0000000000100001 )
b0000011101 *
b0000100 -
10
#519
00
#520
b0000000000100000 )
b0000011100 *
b0001001 -
10
#521
00
#522
b0000000000011111 )
b0000011011 *
b0010010 -
10
#523
00
#524
b0000000000011110 )
b0000011010 *
b0100100 -
10
#525
00
#526
b0000000000011101 )
b0000011001 *
b1001001 -
10
#527
00
#528
b0000000000011100 )
b0000011000 *
b0010011 -
10
#529
00
#530
b0000000000011011 )
b0000010111 *
b0100110 -
10
#531
00
#532
b0000000000011010 )
b0000010110 *
b1001101 -
10
#533
00
#534
b0000000000011001 )
b0000010101 *
b0011010 -
10
#535
00
#536
b0000000000011000 )
b0000010100 *
b0110100 -
10
#537
00
#538
b0000000000010111 )
b0000010011 *
b1101001 -
10
#539
00
#540
b0000000000010110 )
b0000010010 *
b1010011 -
10
#541
00
#542
b0000000000010101 )
b0000010001 *
b0100111 -
10
#543
00
#544
b0000000000010100 )
b0000010000 *
b1001111 -
10
#545
00
#546
b0000000000010011 )
b0000001111 *
b0011110 -
10
#547
00
#548
b0000000000010010 )
b0000001110 *
b0111101 -
10
#549
00
#550
b0000000000010001 )
b0000001101 *
b1111011 -
10
#551
00
#552
b0000000000010000 )
b0000001100 *
b1110111 -
10
#553
00
#554
b0000000000001111 )
b0000001011 *
b1101110 -
10
#555
00
#556
b0000000000001110 )
b0000001010 *
b1011100 -
10
#557
00
#558
b0000000000001101 )
b0000001001 *
b0111000 -
10
#559
00
#560
b0000000000001100 )
b0000001000 *
b1110000 -
10
#561
00
#562
b0000000000001011 )
b0000000111 *
b1100001 -
10
#563
00
#564
b0000000000001010 )
b0000000110 *
b1000011 -
10
#565
00
#566
b0000000000001001 )
b0000000101 *
b0000111 -
10
#567
00
#568
b0000000000001000 )
b0000000100 *
b0001111 -
10
#569
00
#570
b0000000000000111 )
b0000000011 *
b0011111 -
10
#571
00
#572
b0000000000000110 )
b0000000010 *
b0111111 -
10
#573
00
#574
b0000000000000101 )
b0000000001 *
b1111111 -
10
#575
00
#576
b0000000000000100 )
b0000000000 *
b1111110 -
10
#577
00
#578
b0000000000000011 )
b0001111101 *
b1111100 -
10
#579
00
#580
b0000000000000010 )
b0001111100 *
b1111000 -
10
#581
00
#582
b0000000000000001 )
b0001111011 *
b1110001 -
10
#583
00
#584
b0000000000000000 )
b0001111010 *
b1100011 -
10
#585
00
#586
1'
b0000000000101111 )
b0001111001 *
b1000111 -
10
#587
00
#588
b00000000000000000000000000000110 #
b00000000000000000000000000000111 $
0'
b0000000000101110 )
b0001111000 *
b0001110 -
10
b00111111 1
#589
00
#590
b0000000000101101 )
b0001110111 *
b0011101 -
10
#591
00
#592
b0000000000101100 )
b0001110110 *
b0111011 -
10
#593
00
#594
b0000000000101011 )
b0001110101 *
b1110110 -
10
#595
00
#596
b0000000000101010 )
b0001110100 *
b1101100 -
10
#597
00
#598
b0000000000101001 )
b0001110011 *
b1011000 -
10
#599
00
#600
b0000000000101000 )
b0001110010 *
b0110001 -
10
#601
00
#602
b0000000000100111 )
b0001110001 *
b1100010 -
10
#603
00
#604
b0000000000100110 )
b0001110000 *
b1000101 -
10
#605
00
#606
b0000000000100101 )
b0001101111 *
b0001010 -
10
#607
00
#608
b0000000000100100 )
b0001101110 *
b0010100 -
10
#609
00
#610
b0000000000100011 )
b0001101101 *
b0101001 -
10
#611
00
#612
b0000000000100010 )
b0001101100 *
b1010010 -
10
#613
00
#614
b0000000000100001 )
b0001101011 *
b0100101 -
10
#615
00
#616
b0000000000100000 )
b0001101010 *
b1001011 -
10
#617
00
#618
b0000000000011111 )
b0001101001 *
b0010111 -
10
#619
00
#620
b0000000000011110 )
b0001101000 *
b0101111 -
10
#621
00
#622
b0000000000011101 )
b0001100111 *
b1011111 -
10
#623
00
#624
b0000000000011100 )
b0001100110 *
b0111110 -
10
#625
00
#626
b0000000000011011 )
b0001100101 *
b1111101 -
10
#627
00
#628
b0000000000011010 )
b0001100100 *
b1111010 -
10
#629
00
#630
b0000000000011001 )
b0001100011 *
b1110101 -
10
#631
00
#632
b0000000000011000 )
b0001100010 *
b1101010 -
10
#633
00
#634
b0000000000010111 )
b0001100001 *
b1010101 -
10
#635
00
#636
b0000000000010110 )
b0001100000 *
b0101010 -
10
#637
00
#638
b0000000000010101 )
b0001011111 *
b1010100 -
10
#639
00
#640
b0000000000010100 )
b0001011110 *
b0101000 -
10
#641
00
#642
b0000000000010011 )
b0001011101 *
b1010000 -
10
#643
00
#644
b0000000000010010 )
b0001011100 *
b0100001 -
10
#645
00
#646
b0000000000010001 )
b0001011011 *
b1000010 -
10
#647
00
#648
b0000000000010000 )
b0001011010 *
b0000101 -
10
#649
00
#650
b0000000000001111 )
b0001011001 *
b0001011 -
10
#651
00
#652
b0000000000001110 )
b0001011000 *
b0010110 -
10
#653
00
#654
b0000000000001101 )
b0001010111 *
b0101101 -
10
#655
00
#656
b0000000000001100 )
b0001010110 *
b1011011 -
10
#657
00
#658
b0000000000001011 )
b0001010101 *
b0110111 -
10
#659
00
#660
b0000000000001010 )
b0001010100 *
b1101111 -
10
#661
00
#662
b0000000000001001 )
b0001010011 *
b1011110 -
10
#663
00
#664
b0000000000001000 )
b0001010010 *
b0111100 -
10
#665
00
#666
b0000000000000111 )
b0001010001 *
b1111001 -
10
#667
00
#668
b0000000000000110 )
b0001010000 *
b1110011 -
10
#669
00
#670
b0000000000000101 )
b0001001111 *
b1100111 -
10
#671
00
