Lab3-FSM/task4/clktick.sv
module clktick #(
    parameter WIDTH = 16
)(
  // interface signals
  input  logic             clk,      // clock 
  input  logic             rst,      // reset
  input  logic             en,       // enable signal
  input  logic [WIDTH-1:0] N,     	 // clock divided by N+1
  output logic  		   tick      // tick output
);

logic [WIDTH-1:0] count;

always_ff @ (posedge clk or posedge rst)
    if (rst) begin
        tick <= 1'b0;
        count <= N;  
        end
    else if (en) begin
        if (count == 0) begin
            tick <= 1'b1;
            count <= N;
            end
        else begin
            tick <= 1'b0;
            count <= count - 1'b1;
            end
        end
endmodule

Lab3-FSM/task3/f1_fsm.sv
module f1_fsm (
    input   logic       rst,
    input   logic       enclk,
    input   logic       clk,
    output  logic [7:0] data_out
);

    typedef enum { S0, S1, S2, S3, S4, S5, S6, S7, S8 } f1_states;
    f1_states state, next_state;

    always_ff @(posedge clk or posedge rst) begin
        if (rst)
            state <= S0;
        else if (en)
            state <= next_state;
    end

    always_comb 
        case (state)
            S0 : data_out = 8'b00000000;
            S1 : data_out = 8'b00000001;
            S2 : data_out = 8'b00000011;
            S3 : data_out = 8'b00000111;
            S4 : data_out = 8'b00001111;
            S5 : data_out = 8'b00011111;
            S6 : data_out = 8'b00111111;
            S7 : data_out = 8'b01111111;
            S8 : data_out = 8'b11111111;
            default : data_out = 8'b00000000;
        endcase


    always_comb begin
        case (state)
            S0 : next_state = S1;
            S1 : next_state = S2;
            S2 : next_state = S3;
            S3 : next_state = S4;
            S4 : next_state = S5;
            S5 : next_state = S6;
            S6 : next_state = S7;
            S7 : next_state = S8;
            S8 : next_state = S0;
            default : next_state = S0;
        endcase
    end

clktick clocktick (
    .clk(clk),
    .rst(rst),
    .N(47),
    .en(enclk),
    .tick(en)
);

endmodule

Lab3-FSM/task3/f1_fsm.vcd
$version Generated by VerilatedVcd $end
$date Sat Nov  2 00:54:20 2024 $end
$timescale 1ps $end

 $scope module TOP $end
  $var wire  1 % clk $end
  $var wire  8 & data_out [7:0] $end
  $var wire  1 $ enclk $end
  $var wire  1 # rst $end
  $scope module f1_fsm $end
   $var wire  1 % clk $end
   $var wire  8 & data_out [7:0] $end
   $var wire  1 ) en $end
   $var wire  1 $ enclk $end
   $var wire 32 ( next_state [31:0] $end
   $var wire  1 # rst $end
   $var wire 32 ' state [31:0] $end
   $scope module clocktick $end
    $var wire 16 , N [15:0] $end
    $var wire 32 + WIDTH [31:0] $end
    $var wire  1 % clk $end
    $var wire 16 * count [15:0] $end
    $var wire  1 $ en $end
    $var wire  1 # rst $end
    $var wire  1 ) tick $end
   $upscope $end
  $upscope $end
 $upscope $end
$enddefinitions $end


#0
0#
0$
1%
b00000000 &
b00000000000000000000000000000000 '
b00000000000000000000000000000001 (
0)
b0000000000000000 *
b00000000000000000000000000010000 +
b0000000000101111 ,
#1
0%
#2
1#
1%
#3
0%
#4
1%
b0000000000101111 *
#5
0%
#6
0#
1%
#7
0%
#8
1$
1%
#9
0%
#10
1%
b0000000000101110 *
#11
0%
#12
1%
b0000000000101101 *
#13
0%
#14
1%
b0000000000101100 *
#15
0%
#16
1%
b0000000000101011 *
#17
0%
#18
1%
b0000000000101010 *
#19
0%
#20
1%
b0000000000101001 *
#21
0%
#22
1%
b0000000000101000 *
#23
0%
#24
1%
b0000000000100111 *
#25
0%
#26
1%
b0000000000100110 *
#27
0%
#28
1%
b0000000000100101 *
#29
0%
#30
1%
b0000000000100100 *
#31
0%
#32
1%
b0000000000100011 *
#33
0%
#34
1%
b0000000000100010 *
#35
0%
#36
1%
b0000000000100001 *
#37
0%
#38
1%
b0000000000100000 *
#39
0%
#40
1%
b0000000000011111 *
#41
0%
#42
1%
b0000000000011110 *
#43
0%
#44
1%
b0000000000011101 *
#45
0%
#46
1%
b0000000000011100 *
#47
0%
#48
1%
b0000000000011011 *
#49
0%
#50
1%
b0000000000011010 *
#51
0%
#52
1%
b0000000000011001 *
#53
0%
#54
1%
b0000000000011000 *
#55
0%
#56
1%
b0000000000010111 *
#57
0%
#58
1%
b0000000000010110 *
#59
0%
#60
1%
b0000000000010101 *
#61
0%
#62
1%
b0000000000010100 *
#63
0%
#64
1%
b0000000000010011 *
#65
0%
#66
1%
b0000000000010010 *
#67
0%
#68
1%
b0000000000010001 *
#69
0%
#70
1%
b0000000000010000 *
#71
0%
#72
1%
b0000000000001111 *
#73
0%
#74
1%
b0000000000001110 *
#75
0%
#76
1%
b0000000000001101 *
#77
0%
#78
1%
b0000000000001100 *
#79
0%
#80
1%
b0000000000001011 *
#81
0%
#82
1%
b0000000000001010 *
#83
0%
#84
1%
b0000000000001001 *
#85
0%
#86
1%
b0000000000001000 *
#87
0%
#88
1%
b0000000000000111 *
#89
0%
#90
1%
b0000000000000110 *
#91
0%
#92
1%
b0000000000000101 *
#93
0%
#94
1%
b0000000000000100 *
#95
0%
#96
1%
b0000000000000011 *
#97
0%
#98
1%
b0000000000000010 *
#99
0%
#100
1%
b0000000000000001 *
#101
0%
#102
1%
b0000000000000000 *
#103
0%
#104
1%
1)
b0000000000101111 *
#105
0%
#106
1%
b00000001 &
b00000000000000000000000000000001 '
b00000000000000000000000000000010 (
0)
b0000000000101110 *
#107
0%
#108
1%
b0000000000101101 *
#109
0%
#110
1%
b0000000000101100 *
#111
0%
#112
1%
b0000000000101011 *
#113
0%
#114
1%
b0000000000101010 *
#115
0%
#116
1%
b0000000000101001 *
#117
0%
#118
1%
b0000000000101000 *
#119
0%
#120
1%
b0000000000100111 *
#121
0%
#122
1%
b0000000000100110 *
#123
0%
#124
1%
b0000000000100101 *
#125
0%
#126
1%
b0000000000100100 *
#127
0%
#128
1%
b0000000000100011 *
#129
0%
#130
1%
b0000000000100010 *
#131
0%
#132
1%
b0000000000100001 *
#133
0%
#134
1%
b0000000000100000 *
#135
0%
#136
1%
b0000000000011111 *
#137
0%
#138
1%
b0000000000011110 *
#139
0%
#140
1%
b0000000000011101 *
#141
0%
#142
1%
b0000000000011100 *
#143
0%
#144
1%
b0000000000011011 *
#145
0%
#146
1%
b0000000000011010 *
#147
0%
#148
1%
b0000000000011001 *
#149
0%
#150
1%
b0000000000011000 *
#151
0%
#152
1%
b0000000000010111 *
#153
0%
#154
1%
b0000000000010110 *
#155
0%
#156
1%
b0000000000010101 *
#157
0%
#158
1%
b0000000000010100 *
#159
0%
#160
1%
b0000000000010011 *
#161
0%
#162
1%
b0000000000010010 *
#163
0%
#164
1%
b0000000000010001 *
#165
0%
#166
1%
b0000000000010000 *
#167
0%
#168
1%
b0000000000001111 *
#169
0%
#170
1%
b0000000000001110 *
#171
0%
#172
1%
b0000000000001101 *
#173
0%
#174
1%
b0000000000001100 *
#175
0%
#176
1%
b0000000000001011 *
#177
0%
#178
1%
b0000000000001010 *
#179
0%
#180
1%
b0000000000001001 *
#181
0%
#182
1%
b0000000000001000 *
#183
0%
#184
1%
b0000000000000111 *
#185
0%
#186
1%
b0000000000000110 *
#187
0%
#188
1%
b0000000000000101 *
#189
0%
#190
1%
b0000000000000100 *
#191
0%
#192
1%
b0000000000000011 *
#193
0%
#194
1%
b0000000000000010 *
#195
0%
#196
1%
b0000000000000001 *
#197
0%
#198
1%
b0000000000000000 *
#199
0%
#200
1%
1)
b0000000000101111 *
#201
0%
#202
1%
b00000011 &
b00000000000000000000000000000010 '
b00000000000000000000000000000011 (
0)
b0000000000101110 *
#203
0%
#204
1%
b0000000000101101 *
#205
0%
#206
1%
b0000000000101100 *
#207
0%
#208
1%
b0000000000101011 *
#209
0%
#210
1%
b0000000000101010 *
#211
0%
#212
1%
b0000000000101001 *
#213
0%
#214
1%
b0000000000101000 *
#215
0%
#216
1%
b0000000000100111 *
#217
0%
#218
1%
b0000000000100110 *
#219
0%
#220
1%
b0000000000100101 *
#221
0%
#222
1%
b0000000000100100 *
#223
0%
#224
1%
b0000000000100011 *
#225
0%
#226
1%
b0000000000100010 *
#227
0%
#228
1%
b0000000000100001 *
#229
0%
#230
1%
b0000000000100000 *
#231
0%
#232
1%
b0000000000011111 *
#233
0%
#234
1%
b0000000000011110 *
#235
0%
#236
1%
b0000000000011101 *
#237
0%
#238
1%
b0000000000011100 *
#239
0%
#240
1%
b0000000000011011 *
#241
0%
#242
1%
b0000000000011010 *
#243
0%
#244
1%
b0000000000011001 *
#245
0%
#246
1%
b0000000000011000 *
#247
0%
#248
1%
b0000000000010111 *
#249
0%
#250
1%
b0000000000010110 *
#251
0%
#252
1%
b0000000000010101 *
#253
0%
#254
1%
b0000000000010100 *
#255
0%
#256
1%
b0000000000010011 *
#257
0%
#258
1%
b0000000000010010 *
#259
0%
#260
1%
b0000000000010001 *
#261
0%
#262
1%
b0000000000010000 *
#263
0%
#264
1%
b0000000000001111 *
#265
0%
#266
1%
b0000000000001110 *
#267
0%
#268
1%
b0000000000001101 *
#269
0%
#270
1%
b0000000000001100 *
#271
0%
#272
1%
b0000000000001011 *
#273
0%
#274
1%
b0000000000001010 *
#275
0%
#276
1%
b0000000000001001 *
#277
0%
#278
1%
b0000000000001000 *
#279
0%
#280
1%
b0000000000000111 *
#281
0%
#282
1%
b0000000000000110 *
#283
0%
#284
1%
b0000000000000101 *
#285
0%
#286
1%
b0000000000000100 *
#287
0%
#288
1%
b0000000000000011 *
#289
0%
#290
1%
b0000000000000010 *
#291
0%
#292
1%
b0000000000000001 *
#293
0%
#294
1%
b0000000000000000 *
#295
0%
#296
1%
1)
b0000000000101111 *
#297
0%
#298
1%
b00000111 &
b00000000000000000000000000000011 '
b00000000000000000000000000000100 (
0)
b0000000000101110 *
#299
0%
#300
1%
b0000000000101101 *
#301
0%
#302
1%
b0000000000101100 *
#303
0%
#304
1%
b0000000000101011 *
#305
0%
#306
1%
b0000000000101010 *
#307
0%
#308
1%
b0000000000101001 *
#309
0%
#310
1%
b0000000000101000 *
#311
0%
#312
1%
b0000000000100111 *
#313
0%
#314
1%
b0000000000100110 *
#315
0%
#316
1%
b0000000000100101 *
#317
0%
#318
1%
b0000000000100100 *
#319
0%
#320
1%
b0000000000100011 *
#321
0%
#322
1%
b0000000000100010 *
#323
0%
#324
1%
b0000000000100001 *
#325
0%
#326
1%
b0000000000100000 *
#327
0%
#328
1%
b0000000000011111 *
#329
0%
#330
1%
b0000000000011110 *
#331
0%
#332
1%
b0000000000011101 *
#333
0%
#334
1%
b0000000000011100 *
#335
0%
#336
1%
b0000000000011011 *
#337
0%
#338
1%
b0000000000011010 *
#339
0%
#340
1%
b0000000000011001 *
#341
0%
#342
1%
b0000000000011000 *
#343
0%
#344
1%
b0000000000010111 *
#345
0%
#346
1%
b0000000000010110 *
#347
0%
#348
1%
b0000000000010101 *
#349
0%
#350
1%
b0000000000010100 *
#351
0%
#352
1%
b0000000000010011 *
#353
0%
#354
1%
b0000000000010010 *
#355
0%
#356
1%
b0000000000010001 *
#357
0%
#358
1%
b0000000000010000 *
#359
0%
#360
1%
b0000000000001111 *
#361
0%
#362
1%
b0000000000001110 *
#363
0%
#364
1%
b0000000000001101 *
#365
0%
#366
1%
b0000000000001100 *
#367
0%
#368
1%
b0000000000001011 *
#369
0%
#370
1%
b0000000000001010 *
#371
0%
#372
1%
b0000000000001001 *
#373
0%
#374
1%
b0000000000001000 *
#375
0%
#376
1%
b0000000000000111 *
#377
0%
#378
1%
b0000000000000110 *
#379
0%
#380
1%
b0000000000000101 *
#381
0%
#382
1%
b0000000000000100 *
#383
0%
#384
1%
b0000000000000011 *
#385
0%
#386
1%
b0000000000000010 *
#387
0%
#388
1%
b0000000000000001 *
#389
0%
#390
1%
b0000000000000000 *
#391
0%
#392
1%
1)
b0000000000101111 *
#393
0%
#394
1%
b00001111 &
b00000000000000000000000000000100 '
b00000000000000000000000000000101 (
0)
b0000000000101110 *
#395
0%
#396
1%
b0000000000101101 *
#397
0%
#398
1%
b0000000000101100 *
#399
0%
#400
1%
b0000000000101011 *
#401
0%
#402
1%
b0000000000101010 *
#403
0%
#404
1%
b0000000000101001 *
#405
0%
#406
1%
b0000000000101000 *
#407
0%
#408
1%
b0000000000100111 *
#409
0%
#410
1%
b0000000000100110 *
#411
0%
#412
1%
b0000000000100101 *
#413
0%
#414
1%
b0000000000100100 *
#415
0%
#416
1%
b0000000000100011 *
#417
0%
#418
1%
b0000000000100010 *
#419
0%
#420
1%
b0000000000100001 *
#421
0%
#422
1%
b0000000000100000 *
#423
0%
#424
1%
b0000000000011111 *
#425
0%
#426
1%
b0000000000011110 *
#427
0%
#428
1%
b0000000000011101 *
#429
0%
#430
1%
b0000000000011100 *
#431
0%
#432
1%
b0000000000011011 *
#433
0%
#434
1%
b0000000000011010 *
#435
0%
#436
1%
b0000000000011001 *
#437
0%
#438
1%
b0000000000011000 *
#439
0%
#440
1%
b0000000000010111 *
#441
0%
#442
1%
b0000000000010110 *
#443
0%
#444
1%
b0000000000010101 *
#445
0%
#446
1%
b0000000000010100 *
#447
0%
#448
1%
b0000000000010011 *
#449
0%
#450
1%
b0000000000010010 *
#451
0%
#452
1%
b0000000000010001 *
#453
0%
#454
1%
b0000000000010000 *
#455
0%
#456
1%
b0000000000001111 *
#457
0%
#458
1%
b0000000000001110 *
#459
0%
#460
1%
b0000000000001101 *
#461
0%
#462
1%
b0000000000001100 *
#463
0%
#464
1%
b0000000000001011 *
#465
0%
#466
1%
b0000000000001010 *
#467
0%
#468
1%
b0000000000001001 *
#469
0%
#470
1%
b0000000000001000 *
#471
0%
#472
1%
b0000000000000111 *
#473
0%
#474
1%
b0000000000000110 *
#475
0%
#476
1%
b0000000000000101 *
#477
0%
#478
1%
b0000000000000100 *
#479
0%
#480
1%
b0000000000000011 *
#481
0%
#482
1%
b0000000000000010 *
#483
0%
#484
1%
b0000000000000001 *
#485
0%
#486
1%
b0000000000000000 *
#487
0%
#488
1%
1)
b0000000000101111 *
#489
0%
#490
1%
b00011111 &
b00000000000000000000000000000101 '
b00000000000000000000000000000110 (
0)
b0000000000101110 *
#491
0%
#492
1%
b0000000000101101 *
#493
0%
#494
1%
b0000000000101100 *
#495
0%
#496
1%
b0000000000101011 *
#497
0%
#498
1%
b0000000000101010 *
#499
0%
#500
1%
b0000000000101001 *
#501
0%
#502
1%
b0000000000101000 *
#503
0%
#504
1%
b0000000000100111 *
#505
0%
#506
1%
b0000000000100110 *
#507
0%
#508
1%
b0000000000100101 *
#509
0%
#510
1%
b0000000000100100 *
#511
0%
#512
1%
b0000000000100011 *
#513
0%
#514
1%
b0000000000100010 *
#515
0%
#516
1%
b0000000000100001 *
#517
0%
#518
1%
b0000000000100000 *
#519
0%
#520
1%
b0000000000011111 *
#521
0%
#522
1%
b0000000000011110 *
#523
0%
#524
1%
b0000000000011101 *
#525
0%
#526
1%
b0000000000011100 *
#527
0%
#528
1%
b0000000000011011 *
#529
0%
#530
1%
b0000000000011010 *
#531
0%
#532
1%
b0000000000011001 *
#533
0%
#534
1%
b0000000000011000 *
#535
0%
#536
1%
b0000000000010111 *
#537
0%
#538
1%
b0000000000010110 *
#539
0%
#540
1%
b0000000000010101 *
#541
0%
#542
1%
b0000000000010100 *
#543
0%
#544
1%
b0000000000010011 *
#545
0%
#546
1%
b0000000000010010 *
#547
0%
#548
1%
b0000000000010001 *
#549
0%
#550
1%
b0000000000010000 *
#551
0%
#552
1%
b0000000000001111 *
#553
0%
#554
1%
b0000000000001110 *
#555
0%
#556
1%
b0000000000001101 *
#557
0%
#558
1%
b0000000000001100 *
#559
0%
#560
1%
b0000000000001011 *
#561
0%
#562
1%
b0000000000001010 *
#563
0%
#564
1%
b0000000000001001 *
#565
0%
#566
1%
b0000000000001000 *
#567
0%
#568
1%
b0000000000000111 *
#569
0%
#570
1%
b0000000000000110 *
#571
0%
#572
1%
b0000000000000101 *
#573
0%
#574
1%
b0000000000000100 *
#575
0%
#576
1%
b0000000000000011 *
#577
0%
#578
1%
b0000000000000010 *
#579
0%
#580
1%
b0000000000000001 *
#581
0%
#582
1%
b0000000000000000 *
#583
0%
#584
1%
1)
b0000000000101111 *
#585
0%
#586
1%
b00111111 &
b00000000000000000000000000000110 '
b00000000000000000000000000000111 (
0)
b0000000000101110 *
#587
0%
#588
1%
b0000000000101101 *
#589
0%
#590
1%
b0000000000101100 *
#591
0%
#592
1%
b0000000000101011 *
#593
0%
#594
1%
b0000000000101010 *
#595
0%
#596
1%
b0000000000101001 *
#597
0%
#598
1%
b0000000000101000 *
#599
0%
#600
1%
b0000000000100111 *
#601
0%
#602
1%
b0000000000100110 *
#603
0%
#604
1%
b0000000000100101 *
#605
0%
#606
1%
b0000000000100100 *
#607
0%
#608
1%
b0000000000100011 *
#609
0%
#610
1%
b0000000000100010 *
#611
0%
#612
1%
b0000000000100001 *
#613
0%
#614
1%
b0000000000100000 *
#615
0%
#616
1%
b0000000000011111 *
#617
0%
#618
1%
b0000000000011110 *
#619
0%
#620
1%
b0000000000011101 *
#621
0%
#622
1%
b0000000000011100 *
#623
0%
#624
1%
b0000000000011011 *
#625
0%
#626
1%
b0000000000011010 *
#627
0%
#628
1%
b0000000000011001 *
#629
0%
#630
1%
b0000000000011000 *
#631
0%
#632
1%
b0000000000010111 *
#633
0%
#634
1%
b0000000000010110 *
#635
0%
#636
1%
b0000000000010101 *
#637
0%
#638
1%
b0000000000010100 *
#639
0%
#640
1%
b0000000000010011 *
#641
0%
#642
1%
b0000000000010010 *
#643
0%
#644
1%
b0000000000010001 *
#645
0%
#646
1%
b0000000000010000 *
#647
0%
#648
1%
b0000000000001111 *
#649
0%
#650
1%
b0000000000001110 *
#651
0%
#652
1%
b0000000000001101 *
#653
0%
#654
1%
b0000000000001100 *
#655
0%
#656
1%
b0000000000001011 *
#657
0%
#658
1%
b0000000000001010 *
#659
0%
#660
1%
b0000000000001001 *
#661
0%
#662
1%
b0000000000001000 *
#663
0%
#664
1%
b0000000000000111 *
#665
0%
#666
1%
b0000000000000110 *
#667
0%
#668
1%
b0000000000000101 *
#669
0%
#670
1%
b0000000000000100 *
#671
0%
#672
1%
b0000000000000011 *
#673
0%
#674
1%
b0000000000000010 *
#675
0%
#676
1%
b0000000000000001 *
#677
0%
#678
1%
b0000000000000000 *
#679
0%
#680
1%
1)
b0000000000101111 *
#681
0%
#682
1%
b01111111 &
b00000000000000000000000000000111 '
b00000000000000000000000000001000 (
0)
b0000000000101110 *
#683
0%
#684
1%
b0000000000101101 *
#685
0%
#686
1%
b0000000000101100 *
#687
0%
#688
1%
b0000000000101011 *
#689
0%
#690
1%
b0000000000101010 *
#691
0%
#692
1%
b0000000000101001 *
#693
0%
#694
1%
b0000000000101000 *
#695
0%
#696
1%
b0000000000100111 *
#697
0%
#698
1%
b0000000000100110 *
#699
0%
#700
1%
b0000000000100101 *
#701
0%
#702
1%
b0000000000100100 *
#703
0%
#704
1%
b0000000000100011 *
#705
0%
#706
1%
b0000000000100010 *
#707
0%
#708
1%
b0000000000100001 *
#709
0%
#710
1%
b0000000000100000 *
#711
0%
#712
1%
b0000000000011111 *
#713
0%
#714
1%
b0000000000011110 *
#715
0%
#716
1%
b0000000000011101 *
#717
0%
#718
1%
b0000000000011100 *
#719
0%
#720
1%
b0000000000011011 *
#721
0%
#722
1%
b0000000000011010 *
#723
0%
#724
1%
b0000000000011001 *
#725
0%
#726
1%
b0000000000011000 *
#727
0%
#728
1%
b0000000000010111 *
#729
0%
#730
1%
b0000000000010110 *
#731
0%
#732
1%
b0000000000010101 *
#733
0%
#734
1%
b0000000000010100 *
#735
0%
#736
1%
b0000000000010011 *
#737
0%
#738
1%
b0000000000010010 *
#739
0%
#740
1%
b0000000000010001 *
#741
0%
#742
1%
b0000000000010000 *
#743
0%
#744
1%
b0000000000001111 *
#745
0%
#746
1%
b0000000000001110 *
#747
0%
#748
1%
b0000000000001101 *
#749
0%
#750
1%
b0000000000001100 *
#751
0%
#752
1%
b0000000000001011 *
#753
0%
#754
1%
b0000000000001010 *
#755
0%
#756
1%
b0000000000001001 *
#757
0%
#758
1%
b0000000000001000 *
#759
0%
#760
1%
b0000000000000111 *
#761
0%
#762
1%
b0000000000000110 *
#763
0%
#764
1%
b0000000000000101 *
#765
0%
#766
1%
b0000000000000100 *
#767
0%
#768
1%
b0000000000000011 *
#769
0%
#770
1%
b0000000000000010 *
#771
0%
#772
1%
b0000000000000001 *
#773
0%
#774
1%
b0000000000000000 *
#775
0%
#776
1%
1)
b0000000000101111 *
#777
0%
#778
1%
b11111111 &
b00000000000000000000000000001000 '
b00000000000000000000000000000000 (
0)
b0000000000101110 *
#779
0%
#780
1%
b0000000000101101 *
#781
0%
#782
1%
b0000000000101100 *
#783
0%
#784
1%
b0000000000101011 *
#785
0%
#786
1%
b0000000000101010 *
#787
0%
#788
1%
b0000000000101001 *
#789
0%
#790
1%
b0000000000101000 *
#791
0%
#792
1%
b0000000000100111 *
#793
0%
#794
1%
b0000000000100110 *
#795
0%
#796
1%
b0000000000100101 *
#797
0%
#798
1%
b0000000000100100 *
#799
0%
#800
1%
b0000000000100011 *
#801
0%
#802
1%
b0000000000100010 *
#803
0%
#804
1%
b0000000000100001 *
#805
0%
#806
1%
b0000000000100000 *
#807
0%
#808
1%
b0000000000011111 *
#809
0%
#810
1%
b0000000000011110 *
#811
0%
#812
1%
b0000000000011101 *
#813
0%
#814
1%
b0000000000011100 *
#815
0%
#816
1%
b0000000000011011 *
#817
0%
#818
1%
b0000000000011010 *
#819
0%
#820
1%
b0000000000011001 *
#821
0%
#822
1%
b0000000000011000 *
#823
0%
#824
1%
b0000000000010111 *
#825
0%
#826
1%
b0000000000010110 *
#827
0%
#828
1%
b0000000000010101 *
#829
0%
#830
1%
b0000000000010100 *
#831
0%
#832
1%
b0000000000010011 *
#833
0%
#834
1%
b0000000000010010 *
#835
0%
#836
1%
b0000000000010001 *
#837
0%
#838
1%
b0000000000010000 *
#839
0%
#840
1%
b0000000000001111 *
#841
0%
#842
1%
b0000000000001110 *
#843
0%
#844
1%
b0000000000001101 *
#845
0%
#846
1%
b0000000000001100 *
#847
0%
#848
1%
b0000000000001011 *
#849
0%
#850
1%
b0000000000001010 *
#851
0%
#852
1%
b0000000000001001 *
#853
0%
#854
1%
b0000000000001000 *
#855
0%
#856
1%
b0000000000000111 *
#857
0%
#858
1%
b0000000000000110 *
#859
0%
#860
1%
b0000000000000101 *
#861
0%
#862
1%
b0000000000000100 *
#863
0%
#864
1%
b0000000000000011 *
#865
0%
#866
1%
b0000000000000010 *
#867
0%
#868
1%
b0000000000000001 *
#869
0%
#870
1%
b0000000000000000 *
#871
0%
#872
1%
1)
b0000000000101111 *
#873
0%
#874
1%
b00000000 &
b00000000000000000000000000000000 '
b00000000000000000000000000000001 (
0)
b0000000000101110 *
#875
0%
#876
1%
b0000000000101101 *
#877
0%
#878
1%
b0000000000101100 *
#879
0%
#880
1%
b0000000000101011 *
#881
0%
#882
1%
b0000000000101010 *
#883
0%
#884
1%
b0000000000101001 *
#885
0%
#886
1%
b0000000000101000 *
#887
0%
#888
1%
b0000000000100111 *
#889
0%
#890
1%
b0000000000100110 *
#891
0%
#892
1%
b0000000000100101 *
#893
0%
#894
1%
b0000000000100100 *
#895
0%
#896
1%
b0000000000100011 *
#897
0%
#898
1%
b0000000000100010 *
#899
0%
#900
1%
b0000000000100001 *
#901
0%
#902
1%
b0000000000100000 *
#903
0%
#904
1%
b0000000000011111 *
#905
0%
#906
1%
b0000000000011110 *
#907
0%
#908
1%
b0000000000011101 *
#909
0%
#910
1%
b0000000000011100 *
#911
0%
#912
1%
b0000000000011011 *
#913
0%
#914
1%
b0000000000011010 *
#915
0%
#916
1%
b0000000000011001 *
#917
0%
#918
1%
b0000000000011000 *
#919
0%
#920
1%
b0000000000010111 *
#921
0%
#922
1%
b0000000000010110 *
#923
0%
#924
1%
b0000000000010101 *
#925
0%
#926
1%
b0000000000010100 *
#927
0%
#928
1%
b0000000000010011 *
#929
0%
#930
1%
b0000000000010010 *
#931
0%
#932
1%
b0000000000010001 *
#933
0%
#934
1%
b0000000000010000 *
#935
0%
#936
1%
b0000000000001111 *
#937
0%
#938
1%
b0000000000001110 *
#939
0%
#940
1%
b0000000000001101 *
#941
0%
#942
1%
b0000000000001100 *
#943
0%
#944
1%
b0000000000001011 *
#945
0%
#946
1%
b0000000000001010 *
#947
0%
#948
1%
b0000000000001001 *
#949
0%
#950
1%
b0000000000001000 *
#951
0%
#952
1%
b0000000000000111 *
#953
0%
#954
1%
b0000000000000110 *
#955
0%
#956
1%
b0000000000000101 *
#957
0%
#958
1%
b0000000000000100 *
#959
0%
#960
1%
b0000000000000011 *
#961
0%
#962
1%
b0000000000000010 *
#963
0%
#964
1%
b0000000000000001 *
#965
0%
#966
1%
b0000000000000000 *
#967
0%
#968
1%
1)
b0000000000101111 *
#969
0%
#970
1%
b00000001 &
b00000000000000000000000000000001 '
b00000000000000000000000000000010 (
0)
b0000000000101110 *
#971
0%
#972
1%
b0000000000101101 *
#973
0%
#974
1%
b0000000000101100 *
#975
0%
#976
1%
b0000000000101011 *
#977
0%
#978
1%
b0000000000101010 *
#979
0%
#980
1%
b0000000000101001 *
#981
0%
#982
1%
b0000000000101000 *
#983
0%
#984
1%
b0000000000100111 *
#985
0%
#986
1%
b0000000000100110 *
#987
0%
#988
1%
b0000000000100101 *
#989
0%
#990
1%
b0000000000100100 *
#991
0%
#992
1%
b0000000000100011 *
#993
0%
#994
1%
b0000000000100010 *
#995
0%
#996
1%
b0000000000100001 *
#997
0%
#998
1%
b0000000000100000 *
#999
0%
#1000
1%
b0000000000011111 *
#1001
0%
#1002
1%
b0000000000011110 *
#1003
0%
#1004
1%
b0000000000011101 *
#1005
0%
#1006
1%
b0000000000011100 *
#1007
0%
#1008
1%
b0000000000011011 *
#1009
0%
#1010
1%
b0000000000011010 *
#1011
0%
#1012
1%
b0000000000011001 *
#1013
0%
#1014
1%
b0000000000011000 *
#1015
0%
#1016
1%
b0000000000010111 *
#1017
0%
#1018
1%
b0000000000010110 *
#1019
0%
#1020
1%
b0000000000010101 *
#1021
0%
#1022
1%
b0000000000010100 *
#1023
0%
#1024
1%
b0000000000010011 *
#1025
0%
#1026
1%
b0000000000010010 *
#1027
0%
#1028
1%
b0000000000010001 *
#1029
0%
#1030
1%
b0000000000010000 *
#1031
0%
#1032
1%
b0000000000001111 *
#1033
0%
#1034
1%
b0000000000001110 *
#1035
0%
#1036
1%
b0000000000001101 *
#1037
0%
#1038
1%
b0000000000001100 *
#1039
0%
#1040
1%
b0000000000001011 *
#1041
0%
#1042
1%
b0000000000001010 *
#1043
0%
#1044
1%
b0000000000001001 *
#1045
0%
#1046
1%
b0000000000001000 *
#1047
0%
#1048
1%
b0000000000000111 *
#1049
0%
#1050
1%
b0000000000000110 *
#1051
0%
#1052
1%
b0000000000000101 *
#1053
0%
#1054
1%
b0000000000000100 *
#1055
0%
#1056
1%
b0000000000000011 *
#1057
0%
#1058
1%
b0000000000000010 *
#1059
0%
#1060
1%
b0000000000000001 *
#1061
0%
#1062
1%
b0000000000000000 *
#1063
0%
#1064
1%
1)
b0000000000101111 *
#1065
0%
#1066
1%
b00000011 &
b00000000000000000000000000000010 '
b00000000000000000000000000000011 (
0)
b0000000000101110 *
#1067
0%
#1068
1%
b0000000000101101 *
#1069
0%
#1070
1%
b0000000000101100 *
#1071
0%
#1072
1%
b0000000000101011 *
#1073
0%
#1074
1%
b0000000000101010 *
#1075
0%
#1076
1%
b0000000000101001 *
#1077
0%
#1078
1%
b0000000000101000 *
#1079
0%
#1080
1%
b0000000000100111 *
#1081
0%
#1082
1%
b0000000000100110 *
#1083
0%
#1084
1%
b0000000000100101 *
#1085
0%
#1086
1%
b0000000000100100 *
#1087
0%
#1088
1%
b0000000000100011 *
#1089
0%
#1090
1%
b0000000000100010 *
#1091
0%
#1092
1%
b0000000000100001 *
#1093
0%
#1094
1%
b0000000000100000 *
#1095
0%
#1096
1%
b0000000000011111 *
#1097
0%
#1098
1%
b0000000000011110 *
#1099
0%
#1100
1%
b0000000000011101 *
#1101
0%
#1102
1%
b0000000000011100 *
#1103
0%
#1104
1%
b0000000000011011 *
#1105
0%
#1106
1%
b0000000000011010 *
#1107
0%
#1108
1%
b0000000000011001 *
#1109
0%
#1110
1%
b0000000000011000 *
#1111
0%
#1112
1%
b0000000000010111 *
#1113
0%
#1114
1%
b0000000000010110 *
#1115
0%
#1116
1%
b0000000000010101 *
#1117
0%
#1118
1%
b0000000000010100 *
#1119
0%
#1120
1%
b0000000000010011 *
#1121
0%
#1122
1%
b0000000000010010 *
#1123
0%
#1124
1%
b0000000000010001 *
#1125
0%
#1126
1%
b0000000000010000 *
#1127
0%
#1128
1%
b0000000000001111 *
#1129
0%
#1130
1%
b0000000000001110 *
#1131
0%
#1132
1%
b0000000000001101 *
#1133
0%
#1134
1%
b0000000000001100 *
#1135
0%
#1136
1%
b0000000000001011 *
#1137
0%
#1138
1%
b0000000000001010 *
#1139
0%
#1140
1%
b0000000000001001 *
#1141
0%
#1142
1%
b0000000000001000 *
#1143
0%
#1144
1%
b0000000000000111 *
#1145
0%
#1146
1%
b0000000000000110 *
#1147
0%
#1148
1%
b0000000000000101 *
#1149
0%
#1150
1%
b0000000000000100 *
#1151
0%
#1152
1%
b0000000000000011 *
#1153
0%
#1154
1%
b0000000000000010 *
#1155
0%
#1156
1%
b0000000000000001 *
#1157
0%
#1158
1%
b0000000000000000 *
#1159
0%
#1160
1%
1)
b0000000000101111 *
#1161
0%
#1162
1%
b00000111 &
b00000000000000000000000000000011 '
b00000000000000000000000000000100 (
0)
b0000000000101110 *
#1163
0%
#1164
1%
b0000000000101101 *
#1165
0%
#1166
1%
b0000000000101100 *
#1167
0%
#1168
1%
b0000000000101011 *
#1169
0%
#1170
1%
b0000000000101010 *
#1171
0%
#1172
1%
b0000000000101001 *
#1173
0%
#1174
1%
b0000000000101000 *
